transip_stack/__init__.py
transip_stack/__main__.py
transip_stack/exceptions.py
transip_stack/http.py
transip_stack/nodes.py
transip_stack/stack.py
transip_stack/users.py
transip_stack/utils.py
transip_stack_api-1.3.3.dist-info/LICENSE.md
transip_stack_api-1.3.3.dist-info/METADATA
transip_stack_api-1.3.3.dist-info/WHEEL
transip_stack_api-1.3.3.dist-info/entry_points.txt
transip_stack_api-1.3.3.dist-info/top_level.txt
transip_stack_api-1.3.3.dist-info/RECORD
