Metadata-Version: 2.1
Name: transip-stack-api
Version: 1.3.3
Summary: Unofficial wrapper for the TransIP STACK API
Home-page: https://github.com/Paradoxis/TransIP-STACK-API
Author: Luke Paris (Paradoxis)
Author-email: luke@paradoxis.nl
License: MIT
Platform: UNKNOWN
Classifier: License :: OSI Approved :: MIT License
Classifier: Programming Language :: Python
Classifier: Programming Language :: Python :: 3
Classifier: Programming Language :: Python :: 3.6
Classifier: Programming Language :: Python :: Implementation :: CPython
Classifier: Programming Language :: Python :: Implementation :: PyPy
Requires-Python: >=3.5.0
Requires-Dist: bs4 (>=0.0.1)
Requires-Dist: lxml (>=3.8.0)
Requires-Dist: requests (>=2.18.2)
Provides-Extra: dev
Requires-Dist: twine ; extra == 'dev'
Requires-Dist: wheel ; extra == 'dev'
Provides-Extra: test
Requires-Dist: codecov ; extra == 'test'
Requires-Dist: coverage ; extra == 'test'
